{
    "channels": [
        {
            "name": "SR",
            "samples": [
                {
                    "data": [
                        146753488.0,
                        91859048.0,
                        62545012.0,
                        45761176.0,
                        34972856.0,
                        27470240.0,
                        22269518.0,
                        18470844.0,
                        15310497.0,
                        13353816.0,
                        11256135.0,
                        10171135.0,
                        8987735.0,
                        8058657.5,
                        7374664.0,
                        6825259.0,
                        6277418.0,
                        5639445.0,
                        4833536.0,
                        2319333.5
                    ],
                    "modifiers": [
                        {
                            "data": {
                                "hi": 1.3,
                                "lo": 0.7
                            },
                            "name": "NormQCD",
                            "type": "normsys"
                        }
                    ],
                    "name": "QCD"
                },
                {
                    "data": [
                        6040.6728515625,
                        9389.677734375,
                        10075.158203125,
                        10752.5986328125,
                        10893.3125,
                        10969.701171875,
                        10903.3642578125,
                        11224.9970703125,
                        11486.32421875,
                        11536.5791015625,
                        12274.3251953125,
                        12744.7138671875,
                        13920.68359375,
                        15591.1572265625,
                        18517.99609375,
                        21426.740234375,
                        27397.00390625,
                        36008.65625,
                        50554.40234375,
                        77775.078125
                    ],
                    "modifiers": [
                        {
                            "data": null,
                            "name": "mu",
                            "type": "normfactor"
                        }
                    ],
                    "name": "haa_ma40"
                }
            ]
        }
    ],
    "measurements": [
        {
            "config": {
                "parameters": [
                    {
                        "bounds": [
                            [
                                0,
                                1
                            ]
                        ],
                        "inits": [
                            0
                        ],
                        "name": "mu"
                    }
                ],
                "poi": "mu"
            },
            "name": "haa_Br"
        }
    ],
    "observations": [
        {
            "data": [
                146753488.0,
                91859048.0,
                62545012.0,
                45761176.0,
                34972856.0,
                27470240.0,
                22269518.0,
                18470844.0,
                15310497.0,
                13353816.0,
                11256135.0,
                10171135.0,
                8987735.0,
                8058657.5,
                7374664.0,
                6825259.0,
                6277418.0,
                5639445.0,
                4833536.0,
                2319333.5
            ],
            "name": "SR"
        }
    ],
    "version": "1.0.0"
}